<?xml version="1.0" encoding="UTF-8"?>

<xwikidoc>
  <web>Main</web>
  <name>Welcome</name>
  <language>es</language>
  <defaultLanguage/>
  <translation>1</translation>
  <parent>Main.WebHome</parent>
  <creator>xwiki:XWiki.Admin</creator>
  <author>xwiki:XWiki.Admin</author>
  <customClass/>
  <contentAuthor>xwiki:XWiki.Admin</contentAuthor>
  <creationDate>1252454400000</creationDate>
  <date>1297866863000</date>
  <contentUpdateDate>1297866863000</contentUpdateDate>
  <version>1.1</version>
  <title>$services.localization.render('xe.dashboard.wiki.welcome')</title>
  <template/>
  <defaultTemplate/>
  <validationScript/>
  <comment/>
  <minorEdit>false</minorEdit>
  <syntaxId>xwiki/2.0</syntaxId>
  <hidden>false</hidden>
  <content>Este es un sitio web fácil de editar que les ayudará a trabajar mejor juntos. Este Wiki está compuesto de //páginas// organizadas en //espacios//. Usted está actualmente en el espacio principal (**Main**), viendo la página inicial (**WebHome**).

{{velocity}}
#if($hasEdit)Puede utilizar la [[zona de pruebas&gt;&gt;Sandbox.WebHome]] para probar las características del wiki.#end
{{/velocity}}

</content>
</xwikidoc>
